malsearch/VERSION.txt
malsearch/__info__.py
malsearch/__init__.py
malsearch/__main__.py
malsearch/clients/__common__.py
malsearch/clients/__init__.py
malsearch/clients/maldatabase.py
malsearch/clients/malpedia.py
malsearch/clients/malshare.py
malsearch/clients/malwarebazaar.py
malsearch/clients/malwarefeed.py
malsearch/clients/triage.py
malsearch/clients/virusshare.py
malsearch/clients/virustotal.py
malsearch/clients/vxunderground.py
malsearch-0.4.1.dist-info/licenses/LICENSE
malsearch-0.4.1.dist-info/METADATA
malsearch-0.4.1.dist-info/WHEEL
malsearch-0.4.1.dist-info/entry_points.txt
malsearch-0.4.1.dist-info/top_level.txt
malsearch-0.4.1.dist-info/RECORD
