Metadata-Version: 2.4
Name: malsearch
Version: 0.4.1
Summary: Library for getting samples from multiple malware databases
Author-email: Alexandre D'Hondt <alexandre.dhondt@gmail.com>
License:                     GNU GENERAL PUBLIC LICENSE
Project-URL: documentation, https://python-malsearch.readthedocs.io/en/latest/?badge=latest
Project-URL: homepage, https://github.com/dhondta/python-malsearch
Project-URL: issues, https://github.com/dhondta/python-malsearch/issues
Project-URL: repository, https://github.com/dhondta/python-malsearch
Keywords: python,development,programming,malware-samples,malware-database
Classifier: Development Status :: 5 - Production/Stable
Classifier: Environment :: Console
Classifier: Intended Audience :: Developers
Classifier: License :: OSI Approved :: GNU General Public License v3 or later (GPLv3+)
Classifier: Programming Language :: Python :: 3
Classifier: Programming Language :: Python :: 3.9
Classifier: Programming Language :: Python :: 3.10
Classifier: Programming Language :: Python :: 3.11
Classifier: Programming Language :: Python :: 3.12
Classifier: Topic :: Software Development :: Libraries :: Python Modules
Requires-Python: <4,>=3.9
License-File: LICENSE
Requires-Dist: pyzipper
Requires-Dist: requests-cache>=1.2.1
Requires-Dist: requests>=2.32.2
Requires-Dist: urllib3>=1.26.19
Requires-Dist: zipp>=3.19.1
Provides-Extra: codext
Requires-Dist: codext; extra == "codext"
Dynamic: license-file
